{
  "start": 1499,
  "end": 1504,
  "version": 193,
  "docFile": "PHASE_1499_1504_GOVERNANCE_ASSURANCE_STABILITY_CONTINUITY_V193.md",
  "testFile": "src/lib/__tests__/governance-assurance-stability-suite-v193.test.ts",
  "title": "Governance Assurance Stability Continuity V193",
  "modules": [
    {
      "phase": 1499,
      "title": "Governance Assurance Stability Router V193",
      "fileName": "governance-assurance-stability-router-v193.ts",
      "exportBase": "GovernanceAssuranceStability",
      "reportLabel": "Governance assurance stability",
      "reportMessage": "Governance assurance stability routed",
      "mode": "router",
      "signalFields": ["governanceAssurance", "stabilityCoverage", "routerCost"],
      "routeLabels": ["assurance-priority", "assurance-balanced", "assurance-review"]
    },
    {
      "phase": 1500,
      "title": "Policy Recovery Continuity Harmonizer V193",
      "fileName": "policy-recovery-continuity-harmonizer-v193.ts",
      "exportBase": "PolicyRecoveryContinuity",
      "reportLabel": "Policy recovery continuity",
      "reportMessage": "Policy recovery continuity harmonized",
      "mode": "harmonizer",
      "signalFields": ["policyRecovery", "continuityDepth", "harmonizerCost"]
    },
    {
      "phase": 1501,
      "title": "Compliance Stability Continuity Mesh V193",
      "fileName": "compliance-stability-continuity-mesh-v193.ts",
      "exportBase": "ComplianceStabilityContinuity",
      "reportLabel": "Compliance stability continuity",
      "reportMessage": "Compliance stability continuity routed",
      "mode": "router",
      "signalFields": ["complianceStability", "continuityCoverage", "meshCost"],
      "routeLabels": ["compliance-priority", "compliance-balanced", "compliance-review"]
    },
    {
      "phase": 1502,
      "title": "Trust Assurance Recovery Forecaster V193",
      "fileName": "trust-assurance-recovery-forecaster-v193.ts",
      "exportBase": "TrustAssuranceRecovery",
      "reportLabel": "Trust assurance recovery",
      "reportMessage": "Trust assurance recovery forecasted",
      "mode": "forecaster",
      "signalFields": ["trustAssurance", "recoveryDepth", "forecastCost"]
    },
    {
      "phase": 1503,
      "title": "Board Stability Continuity Coordinator V193",
      "fileName": "board-stability-continuity-coordinator-v193.ts",
      "exportBase": "BoardStabilityContinuity",
      "reportLabel": "Board stability continuity",
      "reportMessage": "Board stability continuity coordinated",
      "mode": "coordinator",
      "signalFields": ["boardStability", "continuityCoverage", "coordinationCost"]
    },
    {
      "phase": 1504,
      "title": "Policy Recovery Assurance Engine V193",
      "fileName": "policy-recovery-assurance-engine-v193.ts",
      "exportBase": "PolicyRecoveryAssurance",
      "reportLabel": "Policy recovery assurance",
      "reportMessage": "Policy recovery assurance evaluated",
      "mode": "engine",
      "signalFields": ["policyRecovery", "assuranceDepth", "engineCost"]
    }
  ]
}
