{
  "start": 1613,
  "end": 1618,
  "version": 212,
  "docFile": "PHASE_1613_1618_GOVERNANCE_ASSURANCE_STABILITY_CONTINUITY_V212.md",
  "testFile": "src/lib/__tests__/governance-assurance-stability-suite-v212.test.ts",
  "title": "Governance Assurance Stability Continuity V212",
  "modules": [
    {
      "phase": 1613,
      "title": "Governance Assurance Stability Router V212",
      "fileName": "governance-assurance-stability-router-v212.ts",
      "exportBase": "GovernanceAssuranceStability",
      "reportLabel": "Governance assurance stability",
      "reportMessage": "Governance assurance stability routed",
      "mode": "router",
      "signalFields": ["governanceAssurance", "stabilityCoverage", "routerCost"],
      "routeLabels": ["assurance-priority", "assurance-balanced", "assurance-review"]
    },
    {
      "phase": 1614,
      "title": "Policy Recovery Continuity Harmonizer V212",
      "fileName": "policy-recovery-continuity-harmonizer-v212.ts",
      "exportBase": "PolicyRecoveryContinuity",
      "reportLabel": "Policy recovery continuity",
      "reportMessage": "Policy recovery continuity harmonized",
      "mode": "harmonizer",
      "signalFields": ["policyRecovery", "continuityDepth", "harmonizerCost"]
    },
    {
      "phase": 1615,
      "title": "Compliance Stability Continuity Mesh V212",
      "fileName": "compliance-stability-continuity-mesh-v212.ts",
      "exportBase": "ComplianceStabilityContinuity",
      "reportLabel": "Compliance stability continuity",
      "reportMessage": "Compliance stability continuity routed",
      "mode": "router",
      "signalFields": ["complianceStability", "continuityCoverage", "meshCost"],
      "routeLabels": ["compliance-priority", "compliance-balanced", "compliance-review"]
    },
    {
      "phase": 1616,
      "title": "Trust Assurance Recovery Forecaster V212",
      "fileName": "trust-assurance-recovery-forecaster-v212.ts",
      "exportBase": "TrustAssuranceRecovery",
      "reportLabel": "Trust assurance recovery",
      "reportMessage": "Trust assurance recovery forecasted",
      "mode": "forecaster",
      "signalFields": ["trustAssurance", "recoveryDepth", "forecastCost"]
    },
    {
      "phase": 1617,
      "title": "Board Stability Continuity Coordinator V212",
      "fileName": "board-stability-continuity-coordinator-v212.ts",
      "exportBase": "BoardStabilityContinuity",
      "reportLabel": "Board stability continuity",
      "reportMessage": "Board stability continuity coordinated",
      "mode": "coordinator",
      "signalFields": ["boardStability", "continuityCoverage", "coordinationCost"]
    },
    {
      "phase": 1618,
      "title": "Policy Recovery Assurance Engine V212",
      "fileName": "policy-recovery-assurance-engine-v212.ts",
      "exportBase": "PolicyRecoveryAssurance",
      "reportLabel": "Policy recovery assurance",
      "reportMessage": "Policy recovery assurance evaluated",
      "mode": "engine",
      "signalFields": ["policyRecovery", "assuranceDepth", "engineCost"]
    }
  ]
}
